trallie/__init__.py
trallie/data_handlers.py
trallie/wrappers.py
trallie/data_extraction/__init__.py
trallie/data_extraction/data_extractor.py
trallie/prompts/__init__.py
trallie/prompts/de/data_extraction_prompts.py
trallie/prompts/de/schema_generation_prompts.py
trallie/prompts/en/data_extraction_prompts.py
trallie/prompts/en/schema_generation_prompts.py
trallie/prompts/es/data_extraction_prompts.py
trallie/prompts/es/schema_generation_prompts.py
trallie/prompts/fr/data_extraction_prompts.py
trallie/prompts/fr/schema_generation_prompts.py
trallie/prompts/it/data_extraction_prompts.py
trallie/prompts/it/schema_generation_prompts.py
trallie/providers/__init__.py
trallie/providers/base.py
trallie/providers/errors.py
trallie/providers/groq.py
trallie/providers/huggingface.py
trallie/providers/ollama.py
trallie/providers/openai.py
trallie/schema_generation/__init__.py
trallie/schema_generation/schema_generator.py
trallie-0.1.4.dist-info/METADATA
trallie-0.1.4.dist-info/WHEEL
trallie-0.1.4.dist-info/licenses/LICENSE
trallie-0.1.4.dist-info/RECORD
