Metadata-Version: 2.4
Name: trallie
Version: 0.1.4
Summary: Turning free form text into structured tables
Author-email: Vijayasri Iyer <vijayasri.iyer@picampus-school.com>
License:                                  Apache License
License-File: LICENSE
Requires-Python: >=3.10
Requires-Dist: beautifulsoup4
Requires-Dist: groq
Requires-Dist: huggingface-hub[inference]
Requires-Dist: instructor
Requires-Dist: openai
Requires-Dist: pydantic
Requires-Dist: pypdf2
Provides-Extra: dev
Requires-Dist: black; extra == 'dev'
Requires-Dist: isort; extra == 'dev'
Requires-Dist: pre-commit; extra == 'dev'
Requires-Dist: pylint; extra == 'dev'
Provides-Extra: text
Requires-Dist: pandas; extra == 'text'
Requires-Dist: sentence-transformers; extra == 'text'
